PyInstaller hooks/hook-jill.py
PyInstaller hooks/hook-jupyter_client.py
PyInstaller hooks/hook-qtconsole.py
PyInstaller hooks/hook-spine_engine.py
PyInstaller hooks/hook-spinedb_api.py
PyInstaller hooks/hook-tableschema.py
benchmarks/__init__.py
benchmarks/compound_model_filter_accepts_model.py
benchmarks/db_mngr_get_icon_mngr.py
benchmarks/db_mngr_get_item.py
benchmarks/db_mngr_get_value.py
benchmarks/utils.py
spinetoolbox/__init__.py
spinetoolbox/__main__.py
spinetoolbox/_version.py
spinetoolbox/config.py
spinetoolbox/database_display_names.py
spinetoolbox/execution_managers.py
spinetoolbox/fetch_parent.py
spinetoolbox/file_size_aggregator.py
spinetoolbox/font.py
spinetoolbox/headless.py
spinetoolbox/helpers.py
spinetoolbox/kernel_fetcher.py
spinetoolbox/link.py
spinetoolbox/load_project_items.py
spinetoolbox/log_mixin.py
spinetoolbox/logger.py
spinetoolbox/main.py
spinetoolbox/metaobject.py
spinetoolbox/multi_tab_windows.py
spinetoolbox/parameter_type_validation.py
spinetoolbox/plotting.py
spinetoolbox/plugin_manager.py
spinetoolbox/project.py
spinetoolbox/project_commands.py
spinetoolbox/project_item_icon.py
spinetoolbox/project_settings.py
spinetoolbox/project_upgrader.py
spinetoolbox/qthread_pool_executor.py
spinetoolbox/resources_icons_rc.py
spinetoolbox/resources_logos_rc.py
spinetoolbox/spine_db_commands.py
spinetoolbox/spine_db_icon_manager.py
spinetoolbox/spine_db_manager.py
spinetoolbox/spine_db_parcel.py
spinetoolbox/spine_db_worker.py
spinetoolbox/spine_engine_manager.py
spinetoolbox/spine_engine_worker.py
spinetoolbox/ui_main.py
spinetoolbox/version.py
spinetoolbox/mvcmodels/__init__.py
spinetoolbox/mvcmodels/array_model.py
spinetoolbox/mvcmodels/empty_row_model.py
spinetoolbox/mvcmodels/file_list_models.py
spinetoolbox/mvcmodels/filter_checkbox_list_model.py
spinetoolbox/mvcmodels/filter_execution_model.py
spinetoolbox/mvcmodels/indexed_value_table_model.py
spinetoolbox/mvcmodels/map_model.py
spinetoolbox/mvcmodels/minimal_table_model.py
spinetoolbox-0.10.4.dist-info/licenses/COPYING
spinetoolbox-0.10.4.dist-info/licenses/COPYING.LESSER
spinetoolbox-0.10.4.dist-info/METADATA
spinetoolbox-0.10.4.dist-info/WHEEL
spinetoolbox-0.10.4.dist-info/entry_points.txt
spinetoolbox-0.10.4.dist-info/top_level.txt
spinetoolbox-0.10.4.dist-info/RECORD
