Metadata-Version: 2.4
Name: spinetoolbox
Version: 0.10.4
Summary: An application to define, manage, and execute various energy system simulation models
Author-email: Spine Project consortium <spine_info@vtt.fi>
License: LGPL-3.0-or-later
Project-URL: Documentation, https://spine-toolbox.readthedocs.io/
Project-URL: Repository, https://github.com/spine-tools/Spine-Toolbox
Keywords: energy system modelling,workflow,optimisation,database
Classifier: Programming Language :: Python :: 3
Classifier: License :: OSI Approved :: GNU Lesser General Public License v3 (LGPLv3)
Classifier: Operating System :: OS Independent
Requires-Python: >=3.10
License-File: COPYING
License-File: COPYING.LESSER
Requires-Dist: PySide6>=6.9
Requires-Dist: jupyter_client>=6.0
Requires-Dist: qtconsole>=5.1
Requires-Dist: spinedb_api>=0.36.2
Requires-Dist: spine_engine>=0.26.3
Requires-Dist: numpy>=1.20.2
Requires-Dist: matplotlib>=3.5
Requires-Dist: scipy>=1.7.1
Requires-Dist: networkx>=2.6
Requires-Dist: pandas>=1.3.2
Requires-Dist: Pygments>=2.8
Requires-Dist: jill>=0.9.2
Requires-Dist: pyzmq>=21.0
Requires-Dist: spine_items>=0.24.3
Requires-Dist: pywin32; os_name == "nt"
Dynamic: license-file
